torsiondrive/__init__.py
torsiondrive/_version.py
torsiondrive/dihedral_scanner.py
torsiondrive/extra_constraints.py
torsiondrive/launch.py
torsiondrive/priority_queue.py
torsiondrive/qm_engine.py
torsiondrive/td_api.py
torsiondrive/wq_tools.py
torsiondrive/data/__init__.py
torsiondrive/tests/__init__.py
torsiondrive/tests/test_dihedral_scanner.py
torsiondrive/tests/test_extra_constraints.py
torsiondrive/tests/test_launch.py
torsiondrive/tests/test_priority_queue.py
torsiondrive/tests/test_qm_engine.py
torsiondrive/tests/test_reproduce_examples.py
torsiondrive/tests/test_stack.py
torsiondrive/tests/test_stack_api.py
torsiondrive/tests/test_tools.py
torsiondrive/tests/test_wq_tools.py
torsiondrive/tools/__init__.py
torsiondrive/tools/plot_1d.py
torsiondrive/tools/plot_2d.py
torsiondrive-1.2.0.dist-info/licenses/LICENSE
torsiondrive-1.2.0.dist-info/METADATA
torsiondrive-1.2.0.dist-info/WHEEL
torsiondrive-1.2.0.dist-info/entry_points.txt
torsiondrive-1.2.0.dist-info/top_level.txt
torsiondrive-1.2.0.dist-info/RECORD
