Metadata-Version: 2.4
Name: torsiondrive
Version: 1.2.0
Home-page: https://github.com/lpwgroup/torsiondrive
Author: Yudong Qiu, Lee-Ping Wang
License-File: LICENSE
Requires-Dist: numpy>=1.11
Requires-Dist: geometric>=0.9.7
Dynamic: author
Dynamic: description
Dynamic: home-page
Dynamic: license-file
Dynamic: requires-dist
